Metadata-Version: 1.1
Name: shafdelify
Version: 0.8
Summary: The code behind the great shifdul now automated :)
Home-page: https://github.com/omerka12433/shafdelify
Author: omar mustafa
Author-email: m@omer.com
License: UNKNOWN
Download-URL: https://github.com/omerka12433/shafdelify
Keywords: mustafa,shameless,self,promotion
Platform: UNKNOWN
